pretalx_public_voting/__init__.py
pretalx_public_voting/apps.py
pretalx_public_voting/exporters.py
pretalx_public_voting/forms.py
pretalx_public_voting/models.py
pretalx_public_voting/signals.py
pretalx_public_voting/urls.py
pretalx_public_voting/utils.py
pretalx_public_voting/views.py
pretalx_public_voting/locale/django.pot
pretalx_public_voting/locale/ar/LC_MESSAGES/django.mo
pretalx_public_voting/locale/ar/LC_MESSAGES/django.po
pretalx_public_voting/locale/bg/LC_MESSAGES/django.mo
pretalx_public_voting/locale/bg/LC_MESSAGES/django.po
pretalx_public_voting/locale/ca/LC_MESSAGES/django.mo
pretalx_public_voting/locale/ca/LC_MESSAGES/django.po
pretalx_public_voting/locale/cs/LC_MESSAGES/django.mo
pretalx_public_voting/locale/cs/LC_MESSAGES/django.po
pretalx_public_voting/locale/de_DE/LC_MESSAGES/.gitkeep
pretalx_public_voting/locale/de_DE/LC_MESSAGES/django.mo
pretalx_public_voting/locale/de_DE/LC_MESSAGES/django.po
pretalx_public_voting/locale/de_Formal/LC_MESSAGES/django.mo
pretalx_public_voting/locale/de_Formal/LC_MESSAGES/django.po
pretalx_public_voting/locale/el/LC_MESSAGES/django.mo
pretalx_public_voting/locale/el/LC_MESSAGES/django.po
pretalx_public_voting/locale/es/LC_MESSAGES/django.mo
pretalx_public_voting/locale/es/LC_MESSAGES/django.po
pretalx_public_voting/locale/es_MX/LC_MESSAGES/django.mo
pretalx_public_voting/locale/es_MX/LC_MESSAGES/django.po
pretalx_public_voting/locale/fr_FR/LC_MESSAGES/.gitkeep
pretalx_public_voting/locale/fr_FR/LC_MESSAGES/django.mo
pretalx_public_voting/locale/fr_FR/LC_MESSAGES/django.po
pretalx_public_voting/locale/id/LC_MESSAGES/django.mo
pretalx_public_voting/locale/id/LC_MESSAGES/django.po
pretalx_public_voting/locale/it/LC_MESSAGES/django.mo
pretalx_public_voting/locale/it/LC_MESSAGES/django.po
pretalx_public_voting/locale/ja_JP/LC_MESSAGES/django.mo
pretalx_public_voting/locale/ja_JP/LC_MESSAGES/django.po
pretalx_public_voting/locale/ko/LC_MESSAGES/django.mo
pretalx_public_voting/locale/ko/LC_MESSAGES/django.po
pretalx_public_voting-1.8.0.dist-info/licenses/LICENSE
pretalx_public_voting-1.8.0.dist-info/METADATA
pretalx_public_voting-1.8.0.dist-info/WHEEL
pretalx_public_voting-1.8.0.dist-info/entry_points.txt
pretalx_public_voting-1.8.0.dist-info/top_level.txt
pretalx_public_voting-1.8.0.dist-info/RECORD
