Metadata-Version: 2.4
Name: pretalx-public-voting
Version: 1.8.0
Summary: A public voting plugin for pretalx.
Author-email: Tobias Kunze <r@rixx.de>
Maintainer-email: Tobias Kunze <r@rixx.de>
License: Apache Software License
Project-URL: homepage, https://github.com/pretalx/pretalx-public-voting
Project-URL: repository, https://github.com/pretalx/pretalx-public-voting.git
Keywords: pretalx
License-File: LICENSE
Dynamic: license-file
